[
  {
    "name": "泛科學院",
    "channel_id": "UCATnB3v_NkTTd9iD_4W2A-g"
  },
  {
    "name": "Debug 土撥鼠",
    "channel_id": "UCiMSX1MFvNmgQ77Y4RwLjnw"
  },
  {
    "name": "技术爬爬虾  TechShrimp",
    "channel_id": "UCa6D2k5qhpOI9I-WT8fpd6g"
  },
  {
    "name": "HC AI說人話",
    "channel_id": "UCvGfUB-wBdG4i_TdDGBCwJg"
  },
  {
    "name": "工程師下班有約",
    "channel_id": "UCPLS1Hyv2vTXvMgjO4SMwDw"
  },
  {
    "name": "AI学长小林",
    "channel_id": "UCXYvWkR9LAOsOZjYhghDiXw"
  },
  {
    "name": "AI超元域",
    "channel_id": "UCIomFkAj4Vq_rGX2Jot7D8A"
  },
  {
    "name": "PAPAYA 電腦教室",
    "channel_id": "UCdEpz2A4DzV__4C1x2quKLw"
  }
]